BAAlgorithmUtils/AVLTreeUtil.py
BAAlgorithmUtils/AVLTreeUtilTest.py
BAAlgorithmUtils/AhoCorasickUtil.py
BAAlgorithmUtils/AhoCorasickUtilTest.py
BAAlgorithmUtils/BMUtil.py
BAAlgorithmUtils/BMUtilTest.py
BAAlgorithmUtils/BSTUtil.py
BAAlgorithmUtils/BSTUtilTest.py
BAAlgorithmUtils/ClassUtil.py
BAAlgorithmUtils/HorspoolUtil.py
BAAlgorithmUtils/HorspoolUtilTest.py
BAAlgorithmUtils/KMPUtil.py
BAAlgorithmUtils/KMPUtilTest.py
BAAlgorithmUtils/RBTreeUtil.py
BAAlgorithmUtils/RBTreeUtilTest.py
BAAlgorithmUtils/SBOMUtil.py
BAAlgorithmUtils/SBOMUtilTest.py
BAAlgorithmUtils/SortUtil.py
BAAlgorithmUtils/SortUtilTest.py
BAAlgorithmUtils/TireTreeUtil.py
BAAlgorithmUtils/TireTreeUtilTest.py
BAAlgorithmUtils/__init__.py
BAAlgorithmUtils-3.4.4.dist-info/LICENSE
BAAlgorithmUtils-3.4.4.dist-info/METADATA
BAAlgorithmUtils-3.4.4.dist-info/WHEEL
BAAlgorithmUtils-3.4.4.dist-info/top_level.txt
BAAlgorithmUtils-3.4.4.dist-info/RECORD
