Metadata-Version: 2.1
Name: BAAlgorithmUtils
Version: 3.4.4
Summary: Algorithm utils for python
Home-page: https://github.com/BenArvin/BAAlgorithmUtils
Author: BenArvin
Author-email: benarvin93@outlook.com
License: UNKNOWN
Platform: UNKNOWN
Classifier: Programming Language :: Python :: 3
Classifier: License :: OSI Approved :: MIT License
Classifier: Operating System :: OS Independent
